README.rst
setup.cfg
setup.py
brainite/__init__.py
brainite/info.py
brainite/utils.py
brainite.egg-info/PKG-INFO
brainite.egg-info/SOURCES.txt
brainite.egg-info/dependency_links.txt
brainite.egg-info/requires.txt
brainite.egg-info/top_level.txt
brainite/losses/__init__.py
brainite/losses/mcvae.py
brainite/losses/pmvae.py
brainite/losses/vae.py
brainite/models/__init__.py
brainite/models/mcvae.py
brainite/models/pmvae.py
brainite/models/vae.py
brainite/tests/test_models_mcvae.py
brainite/tests/test_models_pmvae.py
brainite/tests/test_models_vae.py