Metadata-Version: 1.1
Name: brainite
Version: 0.0.0
Summary: 
